decombinator/__init__.py
decombinator/__main__.py
decombinator/collapse.py
decombinator/decombine.py
decombinator/io.py
decombinator/pipeline.py
decombinator/translate.py
decombinator-5.0.1.dist-info/licenses/AUTHORS
decombinator-5.0.1.dist-info/licenses/LICENCE
decombinator-5.0.1.dist-info/METADATA
decombinator-5.0.1.dist-info/WHEEL
decombinator-5.0.1.dist-info/entry_points.txt
decombinator-5.0.1.dist-info/top_level.txt
decombinator-5.0.1.dist-info/RECORD
