Metadata-Version: 2.4
Name: decombinator
Version: 5.0.1
Summary: A fast and efficient tool for the analysis of T-cell receptor repertoire sequences produced by deep sequencing.
Maintainer-email: "Matthew V. Cowley" <m.cowley@ucl.ac.uk>
Project-URL: Homepage, https://github.com/innate2adaptive/Decombinator
Project-URL: Bug Tracker, https://github.com/innate2adaptive/Decombinator/issues
Keywords: decombinator,TCR,TCRseq,repertoire,sequence,analysis
Classifier: Development Status :: 5 - Production/Stable
Classifier: Intended Audience :: Science/Research
Classifier: Topic :: Scientific/Engineering :: Bio-Informatics
Classifier: License :: OSI Approved :: MIT License
Classifier: Programming Language :: Python :: 3.9
Classifier: Programming Language :: Python :: 3.10
Classifier: Programming Language :: Python :: 3.11
Classifier: Programming Language :: Python :: 3.12
Requires-Python: >=3.9
License-File: LICENCE
License-File: AUTHORS
Requires-Dist: acora==2.4
Requires-Dist: biopython==1.84
Requires-Dist: contourpy==1.2.1
Requires-Dist: coverage==7.5.4
Requires-Dist: cycler==0.12.1
Requires-Dist: fonttools==4.53.1
Requires-Dist: igraph==0.11.6
Requires-Dist: iniconfig==2.0.0
Requires-Dist: joblib==1.4.2
Requires-Dist: kiwisolver==1.4.5
Requires-Dist: Levenshtein==0.25.1
Requires-Dist: logomaker==0.8
Requires-Dist: matplotlib==3.9.2
Requires-Dist: networkx==3.2.1
Requires-Dist: numpy==2.0.0
Requires-Dist: packaging==24.1
Requires-Dist: pandas==2.2.2
Requires-Dist: pillow==10.4.0
Requires-Dist: pluggy==1.5.0
Requires-Dist: polyleven==0.8
Requires-Dist: pyparsing==3.1.2
Requires-Dist: pyrepseq==1.5
Requires-Dist: python-dateutil==2.9.0.post0
Requires-Dist: pytz==2024.1
Requires-Dist: rapidfuzz==3.9.4
Requires-Dist: regex==2024.5.15
Requires-Dist: scikit-learn==1.5.1
Requires-Dist: scipy==1.13.1
Requires-Dist: seaborn==0.13.2
Requires-Dist: six==1.16.0
Requires-Dist: texttable==1.7.0
Requires-Dist: threadpoolctl==3.5.0
Requires-Dist: tidytcells==2.1.3
Requires-Dist: tzdata==2024.1
Provides-Extra: dev
Requires-Dist: pytest==8.2.2; extra == "dev"
Requires-Dist: pytest-cov==5.0.0; extra == "dev"
Dynamic: license-file
